neurotools/__init__.py
neurotools/decomposition/__init__.py
neurotools/decomposition/base.py
neurotools/decomposition/canica.py
neurotools/decomposition/dict_learning.py
neurotools/decomposition/multi_pca.py
neurotools/loading/__init__.py
neurotools/loading/abcd.py
neurotools/loading/cache.py
neurotools/loading/from_data.py
neurotools/loading/funcs.py
neurotools/loading/outliers.py
neurotools/loading/parcels.py
neurotools/loading/space.py
neurotools/loading/tests/__init__.py
neurotools/loading/tests/test_funcs.py
neurotools/loading/tests/test_space.py
neurotools/misc/__init__.py
neurotools/misc/print.py
neurotools/misc/text.py
neurotools/networks/__init__.py
neurotools/networks/measures.py
neurotools/networks/tests/__init__.py
neurotools/networks/tests/test_measures.py
neurotools/plotting/__init__.py
neurotools/plotting/funcs.py
neurotools/plotting/network.py
neurotools/plotting/plot.py
neurotools/plotting/plot_single_surf.py
neurotools/plotting/ref.py
neurotools/plotting/tests/__init__.py
neurotools/plotting/tests/test_plot.py
neurotools/random/__init__.py
neurotools/random/parcellation.py
neurotools/random/permute_blocks.py
neurotools/random/tests/__init__.py
neurotools/random/tests/test_parcellation.py
neurotools/random/tests/test_permute_blocks.py
neurotools/rely/__init__.py
neurotools/rely/funcs.py
neurotools/rely/tests/__init__.py
neurotools/rely/tests/test_funcs.py
neurotools/resample/__init__.py
neurotools/resample/general.py
neurotools/resample/vol.py
neurotools/resample/wrappers.py
neurotools/stats/__init__.py
neurotools/stats/_base_run_permutation.py
neurotools/stats/_tf_run_permutation.py
neurotools/stats/basic.py
neurotools/stats/mixed_model.py
neurotools/stats/orth.py
neurotools/stats/permutations.py
neurotools/stats/tests/__init__.py
neurotools/stats/tests/test_permutations.py
neurotools/transform/__init__.py
neurotools/transform/conv.py
neurotools/transform/formats.py
neurotools/transform/network.py
neurotools/transform/parc.py
bp_neurotools-0.24.dist-info/METADATA
bp_neurotools-0.24.dist-info/WHEEL
bp_neurotools-0.24.dist-info/top_level.txt
bp_neurotools-0.24.dist-info/RECORD
