Metadata-Version: 2.1
Name: bp-neurotools
Version: 0.24
Summary: General helper functions for working with neuroimaging data.
Home-page: http://github.com/sahahn/neurotools
Author: Sage Hahn
Author-email: sahahn@uvm.edu
License: MIT
Platform: UNKNOWN
Requires-Python: >=3.7
Requires-Dist: scikit-learn (>=1)
Requires-Dist: scipy
Requires-Dist: numpy
Requires-Dist: pandas (>=1.1)
Requires-Dist: nibabel (>=3.2.1)
Requires-Dist: joblib
Requires-Dist: statsmodels (>=0.13.2)
Requires-Dist: matplotlib (>=3.3.4)
Requires-Dist: nilearn (>=0.8.1)
Requires-Dist: networkx
Requires-Dist: seaborn
